{
  "pl": {
    "title": "KDZ 02/2005 Rura PP kanalizacji wewnętrznej DN32-110 (PN-EN 1451-1)",
    "category": [
      "certyfikaty"
    ],
    "language": "PL",
    "isArchive": false,
    "url": "/documents/KDZ 02:2005 Rura PP kanalizacji wewnetrznej DN32-110 (PN-EN 1451-1).pdf",
    "date": "12.07.2005"
  },
  "en": {
    "title": "KDZ 02/2005 PP Internal Sewage Pipes DN32-110 (PN-EN 1451-1)",
    "category": [
      "certyfikaty"
    ],
    "language": "PL",
    "isArchive": false,
    "url": "/documents/KDZ 02:2005 Rura PP kanalizacji wewnetrznej DN32-110 (PN-EN 1451-1).pdf",
    "date": "12.07.2005"
  }
}
